setup.py
testWrt/__init__.py
testWrt/testsetup.py
testWrt/wifinodes.py
testWrt.egg-info/PKG-INFO
testWrt.egg-info/SOURCES.txt
testWrt.egg-info/dependency_links.txt
testWrt.egg-info/requires.txt
testWrt.egg-info/top_level.txt
testWrt/lib/__init__.py
testWrt/lib/base.py
testWrt/lib/gpio.py
testWrt/lib/log.py
testWrt/lib/rpcd.py
testWrt/lib/ssh.py
testWrt/lib/testing.py
testWrt/lib/ubus.py
testWrt/lib/uci.py
testWrt/lib/uci_api.py
testWrt/utils/__init__.py
testWrt/utils/syslog_receiver.py