Metadata-Version: 1.1
Name: testWrt
Version: 0.1.0
Summary: A small testing library to test OpenWrt devices
Home-page: https://github.com/lynxis/testWrt
Author: Alexander Couzens
Author-email: lynxis@fe80.eu
License: BSD
Keywords: openwrt testing
Platform: UNKNOWN
Classifier: Development Status :: 3 - Alpha
Classifier: Intended Audience :: Developers
Classifier: Topic :: Software Development :: Testing
Classifier: License :: OSI Approved :: BSD License
Classifier: Programming Language :: Python :: 3
Classifier: Programming Language :: Python :: 3.2
Classifier: Programming Language :: Python :: 3.3
Classifier: Programming Language :: Python :: 3.4
